{
  "context_analysis": "博主分享了从手动编码转向AI辅助开发的亲身经历——用2周时间从零学习Rust重建了整个桌面应用，意识到编码不再是核心竞争力。文章核心论点是：AI消除了实现瓶颈后，曾经的\"软技能\"（系统思维、沟通、架构",
  "id": "mz73sVy6-X8",
  "type": "youtube",
  "title": "I Stopped Writing Code - These 5 Skills Are All That Matter",
  "author": "Dave Ebbelaar",
  "date": "2026-03-27",
  "dateText": "Mar 27",
  "duration": "10:30",
  "tldr": "AI消除编码瓶颈后，工程师的核心竞争力从写代码转向系统思维、全栈视角、精准沟通、代码简化能力及测试能力——这些曾经被视为\"软技能\"的能力现在决定了能否交付真正优秀的产品。",
  "takeaways": [
    "系统思维是AI时代的核心能力：不需要懂每行代码，但必须理解组件级别的架构、数据流向和故障模式",
    "全栈能力成为必需：AI可以同时处理前端、数据库、后端，但需要有人理解全局来指挥协调",
    "沟通质量直接决定代码质量：自然语言已成为新的编程语言，输入的清晰度决定输出的精确度",
    "代码简化是专业能力的分水岭：AI容易产生代码膨胀，需要主动删减和重构才能保持代码库健康",
    "测试是AI时代不可妥协的底线：AI倾向于过度乐观并生成mock测试，必须由人来确保真正的测试覆盖和边界条件"
  ],
  "quote": "We've just created a higher abstraction layer. — 我们只是创造了一个更高的抽象层。",
  "link": "https://www.youtube.com/watch?v=mz73sVy6-X8",
  "tags": [
    "AI Engineer Skills",
    "System Thinking",
    "Full Stack Development",
    "Prompt Engineering",
    "Code Quality",
    "Testing Strategy"
  ],
  "detailedBreakdown": [
    {
      "subtitle": "范式转换：从编码到系统思维",
      "points": [
        {
          "label": "核心观点归纳",
          "content": "软件实现的瓶颈已被消除，30年的编程学习路径（教程、训练营、语言 mastery）不再是核心竞争因素，取而代之的是架构设计、系统思维等原本属于高级工程师的能力"
        },
        {
          "label": "关键数据/案例",
          "content": "作者从未写过Rust，用2周时间通过AI重建了整个桌面应用，运行效果优于旧版本，唯一手动干预引入了bug"
        },
        {
          "label": "AI PM 视角/启发",
          "content": "AI产品经理需要理解技术架构层面的能力要求正在发生根本性变化，招聘和团队建设的标准需要重新定义"
        }
      ]
    },
    {
      "subtitle": "技能一：用构建块思维替代代码行思维",
      "points": [
        {
          "label": "核心观点归纳",
          "content": "不需要理解代码的行级别细节，但必须理解组件级别：系统有哪些构建块、如何连接、数据如何在块之间流动、单块故障时会发生什么"
        },
        {
          "label": "关键数据/案例",
          "content": "Rust项目成功的关键不是懂Rust语法，而是理解数据从后端到前端的架构、需要哪些组件、如何将它们连接"
        },
        {
          "label": "AI PM 视角/启发",
          "content": "建议阅读《Designing Data-Intensive Applications》学习系统设计思维，在任何AI项目开始前先研究目标应用类型的架构模式和最佳实践"
        },
        {
          "label": "技术逻辑拆解",
          "content": "使用AI时不要直接让AI\"建一个应用\"，而是先描述系统应该长什么样、组件关系如何、数据流如何设计"
        }
      ]
    },
    {
      "subtitle": "技能二：成为全栈工程师",
      "points": [
        {
          "label": "核心观点归纳",
          "content": "AI可以处理任何语言和框架，超级专精反而成为瓶颈。全栈能力意味着能理解全局并指导AI在各个层面协调工作"
        },
        {
          "label": "AI PM 视角/启发",
          "content": "Practical challenge：用一周时间用从未用过的语言从零构建并部署一个端到端解决方案，体验语言壁垒如何被消除，系统理解才是真正的壁垒"
        },
        {
          "label": "局限与挑战",
          "content": "不需要成为每个领域的专家，但需要足够熟练地指挥AI贯穿整个技术栈"
        }
      ]
    },
    {
      "subtitle": "技能三：沟通即代码",
      "points": [
        {
          "label": "核心观点归纳",
          "content": "我们过去写代码给计算机指令，现在用自然语言给AI指令再生成代码——自然语言已成为新的编程语言，输出质量与输入清晰度成正比"
        },
        {
          "label": "AI PM 视角/启发",
          "content": "作者推荐使用语音转文字应用来写prompt，因为说话时必须大声组织思维，能显著提升prompt质量和速度"
        },
        {
          "label": "技术逻辑拆解",
          "content": "模糊指令→模糊代码，精确、结构化描述→高质量输出；同一模型完全不同结果，差异在于沟通方式"
        }
      ]
    },
    {
      "subtitle": "技能四：计划大格局，执行狠简化",
      "points": [
        {
          "label": "核心观点归纳",
          "content": "AI倾向于输出大量token、产生代码膨胀（AI slop），这反而会导致花在调试上的时间超过AI带来的效率收益"
        },
        {
          "label": "AI PM 视角/启发",
          "content": "专业与\"纯编码\"的区别在于维护简洁干净代码库的能力：建立流程循环（计划→构建→测试→简化），其中简化是大多数人跳过的关键步骤"
        },
        {
          "label": "技术逻辑拆解",
          "content": "简化阶段要不断追问：哪些代码行可以删除仍能通过测试？命名惯例、代码结构、文件结构是否合理？最终目标是找到最核心的构建块，移除任何一项就导致系统不工作"
        }
      ]
    },
    {
      "subtitle": "技能五：测试、测试、测试",
      "points": [
        {
          "label": "核心观点归纳",
          "content": "这是AI时代不可妥协的底线。AI往往过度乐观，会写mock测试来绕过真正需要测试的内容"
        },
        {
          "label": "AI PM 视角/启发",
          "content": "需要熟悉所用语言和项目的测试框架，理解不同类型测试的区别，主动思考\"什么可能真正出错\"、\"有哪些边界条件需要覆盖\""
        },
        {
          "label": "技术逻辑拆解",
          "content": "可以在项目中添加skill让AI创建更好的测试，而非盲目信任AI生成的测试；将测试集成到CI/CD流程中实现自动化"
        }
      ]
    }
  ]
}